edman_web/__init__.py
edman_web/file_manager.py
edman_web/py.typed
edman_web/search_manager.py
venv/bin/jp.py
edman_web-2025.1.31.dist-info/LICENSE.txt
edman_web-2025.1.31.dist-info/METADATA
edman_web-2025.1.31.dist-info/WHEEL
edman_web-2025.1.31.dist-info/top_level.txt
edman_web-2025.1.31.dist-info/RECORD
