Metadata-Version: 2.2
Name: edman_web
Version: 2025.1.31
Summary: Sub-package of edman for web applications.
Author-email: Masaki Ohno <masakio@post.kek.jp>
License: MIT License
Project-URL: documentation, https://ryde.github.io/edman_web/
Project-URL: repository, https://github.com/ryde/edman_web
Classifier: Programming Language :: Python :: 3
Classifier: Programming Language :: Python :: 3.12
Classifier: License :: OSI Approved :: MIT License
Classifier: Topic :: Database :: Front-Ends
Requires-Python: >=3.12
License-File: LICENSE.txt
Requires-Dist: pymongo~=4.11
Requires-Dist: edman~=2025.1.31
Requires-Dist: Werkzeug~=3.1.3
Requires-Dist: Pillow~=11.1.0
Requires-Dist: numpy~=2.2.2
Requires-Dist: opencv-python~=4.11.0.86
Requires-Dist: imutils~=0.5.4
